srai-0.10.2.dist-info/METADATA
srai-0.10.2.dist-info/WHEEL
srai-0.10.2.dist-info/entry_points.txt
srai-0.10.2.dist-info/licenses/LICENSE.md
srai/__init__.py
srai/_optional.py
srai/_typing.py
srai/benchmark/__init__.py
srai/benchmark/_base.py
srai/benchmark/_custom_metrics.py
srai/benchmark/hex_regression_evaluator.py
srai/benchmark/mobility_prediction_evaluator.py
srai/benchmark/trajectory_regression_evaluator.py
srai/constants.py
srai/datasets/__init__.py
srai/datasets/_base.py
srai/datasets/airbnb_multicity.py
srai/datasets/chicago_crime.py
srai/datasets/geolife.py
srai/datasets/house_sales_in_king_county.py
srai/datasets/philadelphia_crime.py
srai/datasets/police_department_incidents.py
srai/datasets/porto_taxi.py
srai/embedders/__init__.py
srai/embedders/_base.py
srai/embedders/_pytorch_stubs.py
srai/embedders/contextual_count_embedder.py
srai/embedders/count_embedder.py
srai/embedders/geovex/__init__.py
srai/embedders/geovex/dataset.py
srai/embedders/geovex/embedder.py
srai/embedders/geovex/model.py
srai/embedders/gtfs2vec/__init__.py
srai/embedders/gtfs2vec/embedder.py
srai/embedders/gtfs2vec/model.py
srai/embedders/hex2vec/__init__.py
srai/embedders/hex2vec/embedder.py
srai/embedders/hex2vec/model.py
srai/embedders/hex2vec/neighbour_dataset.py
srai/embedders/highway2vec/__init__.py
srai/embedders/highway2vec/embedder.py
srai/embedders/highway2vec/model.py
srai/embedders/s2vec/__init__.py
srai/embedders/s2vec/dataset.py
srai/embedders/s2vec/embedder.py
srai/embedders/s2vec/model.py
srai/embedders/s2vec/positional_encoding.py
srai/embedders/s2vec/s2_utils.py
srai/exceptions.py
srai/geometry.py
srai/h3.py
srai/joiners/__init__.py
srai/joiners/_base.py
srai/joiners/intersection_joiner.py
srai/loaders/__init__.py
srai/loaders/_base.py
srai/loaders/download.py
srai/loaders/geoparquet_loader.py
srai/loaders/gtfs_loader.py
srai/loaders/osm_loaders/__init__.py
srai/loaders/osm_loaders/_base.py
srai/loaders/osm_loaders/filters/__init__.py
srai/loaders/osm_loaders/filters/_typing.py
srai/loaders/osm_loaders/filters/base_osm_groups.py
srai/loaders/osm_loaders/filters/geofabrik.py
srai-0.10.2.dist-info/RECORD
