Metadata-Version: 2.1
Name: srai
Version: 0.10.2
Summary: A set of python modules for geospatial machine learning and data mining
Author-Email: Piotr Gramacki <pgramacki@kraina.ai>, =?utf-8?q?Kacper_Le=C5=9Bniara?= <klesniara@kraina.ai>, Kamil Raczycki <kraczycki@kraina.ai>, =?utf-8?q?Szymon_Wo=C5=BAniak?= <swozniak@kraina.ai>
License: Apache-2.0
Classifier: Development Status :: 3 - Alpha
Classifier: License :: OSI Approved :: Apache Software License
Classifier: Topic :: Scientific/Engineering :: Artificial Intelligence
Classifier: Topic :: Scientific/Engineering :: GIS
Classifier: Intended Audience :: Science/Research
Classifier: Intended Audience :: Developers
Classifier: Programming Language :: Python :: 3
Classifier: Programming Language :: Python :: 3.9
Classifier: Programming Language :: Python :: 3.10
Classifier: Programming Language :: Python :: 3.11
Classifier: Programming Language :: Python :: 3.12
Classifier: Operating System :: Unix
Classifier: Operating System :: MacOS
Classifier: Operating System :: Microsoft :: Windows
Project-URL: Homepage, https://kraina-ai.github.io/srai
Project-URL: Repository, https://github.com/kraina-ai/srai
Project-URL: Documentation, https://kraina-ai.github.io/srai
Project-URL: Changelog, https://github.com/kraina-ai/srai/blob/main/CHANGELOG.md
Requires-Python: >=3.9
Requires-Dist: pandas
Requires-Dist: geopandas>=0.6
Requires-Dist: shapely>=2.0.1
Requires-Dist: h3>=4.0.0b1
Requires-Dist: numpy>=1.26.0
Requires-Dist: pyfunctional>=1.0.0
Requires-Dist: pyarrow>=13.0.0
Requires-Dist: topojson>=1.6
Requires-Dist: tqdm>=4.42.0
Requires-Dist: s2>=0.1.9
Requires-Dist: typeguard>=3.0.0
Requires-Dist: requests
Requires-Dist: h3ronpy>=0.20.1
Requires-Dist: osmnx>=1.3.0
Requires-Dist: polars>=0.19.4
Provides-Extra: osm
Requires-Dist: overpass>=0.7; extra == "osm"
Requires-Dist: pillow>=8.0.0; extra == "osm"
Requires-Dist: beautifulsoup4; extra == "osm"
Requires-Dist: quackosm>=0.11.0; extra == "osm"
Provides-Extra: overturemaps
Requires-Dist: overturemaestro>=0.5.0; extra == "overturemaps"
Provides-Extra: datasets
Requires-Dist: datasets<4,>=3; extra == "datasets"
Requires-Dist: fastdtw>=0.3.4; extra == "datasets"
Provides-Extra: voronoi
Requires-Dist: pymap3d>=3.0.0; extra == "voronoi"
Requires-Dist: haversine>=2.0.0; extra == "voronoi"
Requires-Dist: scipy>=1.10.0; extra == "voronoi"
Requires-Dist: spherical-geometry>=1.3.2; extra == "voronoi"
Provides-Extra: gtfs
Requires-Dist: gtfs-kit==6.*; extra == "gtfs"
Provides-Extra: plotting
Requires-Dist: folium>=0.14.0; extra == "plotting"
Requires-Dist: mapclassify>=2.4.0; extra == "plotting"
Requires-Dist: scikit-learn>=1.2.0; extra == "plotting"
Requires-Dist: matplotlib>=3.2.0; extra == "plotting"
Requires-Dist: plotly>=4.6.0; extra == "plotting"
Requires-Dist: kaleido<=0.2.1,>=0.2.0; extra == "plotting"
Provides-Extra: torch
Requires-Dist: pytorch-lightning>=2.0.0; extra == "torch"
Requires-Dist: torch; extra == "torch"
Requires-Dist: timm>=0.9.0; extra == "torch"
Provides-Extra: all
Requires-Dist: srai[datasets,gtfs,osm,overturemaps,plotting,torch,voronoi]; extra == "all"
